spectral_trend_database/__init__.py
spectral_trend_database/cli.py
spectral_trend_database/config.py
spectral_trend_database/constants.py
spectral_trend_database/gcp.py
spectral_trend_database/interface.py
spectral_trend_database/npxr.py
spectral_trend_database/paths.py
spectral_trend_database/query.py
spectral_trend_database/runner.py
spectral_trend_database/smoothing.py
spectral_trend_database/spectral.py
spectral_trend_database/types.py
spectral_trend_database/utils.py
spectral_trend_database/gee/__init__.py
spectral_trend_database/gee/landsat.py
spectral_trend_database/gee/utils.py
spectral_trend_database-0.0.1.dist-info/LICENSE.md
spectral_trend_database-0.0.1.dist-info/METADATA
spectral_trend_database-0.0.1.dist-info/WHEEL
spectral_trend_database-0.0.1.dist-info/entry_points.txt
spectral_trend_database-0.0.1.dist-info/top_level.txt
spectral_trend_database-0.0.1.dist-info/RECORD
