Metadata-Version: 2.2
Name: spectral_trend_database
Version: 0.0.1
License-File: LICENSE.md
Requires-Dist: twine
Requires-Dist: python-geohash<0.9,>=0.8.5
Requires-Dist: build<2,>=1.2.2.post1
Requires-Dist: mproc<0.0.0.5,>=0.0.0.4
